openapi_agent_tools/__init__.py
openapi_agent_tools/parse_open_api_doc.py
openapi_agent_tools/parse_openapi.py
openapi_agent_tools/schema_validator.py
openapi_agent_tools/tool_schema_validator.py
openapi_agent_tools-0.2.0.dist-info/METADATA
openapi_agent_tools-0.2.0.dist-info/WHEEL
openapi_agent_tools-0.2.0.dist-info/top_level.txt
openapi_agent_tools-0.2.0.dist-info/RECORD
