Metadata-Version: 2.2
Name: openapi_agent_tools
Version: 0.2.0
Summary: Generation and validation of Claude-compatible tools from OpenAPI specifications
Author-email: Théo Tenaguillo <theo.tenaguillo@gmail.com>
License: MIT
Project-URL: Bug Reports, https://github.com/username/openapi-agent-tools/issues
Project-URL: Source, https://github.com/username/openapi-agent-tools
Keywords: openapi,claude,anthropic,ai,tools,api
Classifier: Programming Language :: Python :: 3
Classifier: License :: OSI Approved :: MIT License
Classifier: Operating System :: OS Independent
Classifier: Development Status :: 3 - Alpha
Classifier: Intended Audience :: Developers
Classifier: Topic :: Software Development :: Libraries :: Python Modules
Requires-Python: >=3.7
Requires-Dist: PyYAML>=5.4.0
Requires-Dist: ruamel.yaml>=0.17.0
